.gitlab-ci.yml
LICENSE.txt
MANIFEST.in
README.md
ci_build_deb.sh
citysketch_logo.png
pyproject.toml
setup.py
citysketch/App3dview.py
citysketch/AppDialogs.py
citysketch/AppMain.py
citysketch/AppSettings.py
citysketch/Building.py
citysketch/ColorDialogs.py
citysketch/GeoJSON.py
citysketch/__init__.py
citysketch/__main__.py
citysketch/_metadata.py
citysketch/_version.py
citysketch/austaltxt.py
citysketch/building_simplification.py
citysketch/citysketch_logo.png
citysketch/utils.py
docs/3d-visualization.rst
docs/Makefile
docs/basemaps-geotiff.rst
docs/conf.py
docs/creating-buildings.rst
docs/editing-buildings.rst
docs/file-formats.rst
docs/getting-started.rst
docs/index.rst
docs/keyboard-shortcuts.rst
docs/troubleshooting.rst
docs/user-interface.rst
docs/_static/citysketch_logo.png
docs/_static/citysketch_window.png
docs/_static/custom.css
docs/appendix/acknowledgments.rst
docs/appendix/license.rst
docs/technical/api-reference.rst